savingfunds/__init__.py
savingfunds/cli.py
savingfunds/dataloader.py
savingfunds/datasaver.py
savingfunds/funds.py
savingfunds/reporting.py
savingfunds/utils.py
savingfunds/commands/__init__.py
savingfunds/commands/delete_commands.py
savingfunds/commands/distribution_commands.py
savingfunds/commands/edit_commands.py
savingfunds/commands/money_commands.py
savingfunds/commands/new_commands.py
savingfunds/commands/reporting_commands.py
savingfunds/commands/utils.py
savingfunds-0.3.1.dist-info/METADATA
savingfunds-0.3.1.dist-info/WHEEL
savingfunds-0.3.1.dist-info/entry_points.txt
savingfunds-0.3.1.dist-info/licenses/LICENSE
savingfunds-0.3.1.dist-info/RECORD
