Metadata-Version: 2.1
Name: savingfunds
Version: 0.3.1
Summary: A small tool to manage saving for goals
Project-URL: Homepage, https://github.com/dhoekstra2000/savingfunds
Project-URL: Issues, https://github.com/dhoekstra2000/savingfunds/issues
Author-email: Douwe Hoekstra <douwe@35524.xyz>
License-File: LICENSE
Classifier: License :: OSI Approved :: MIT License
Classifier: Operating System :: OS Independent
Classifier: Programming Language :: Python :: 3
Requires-Python: >=3.9
Requires-Dist: click>=8.1.7
Requires-Dist: pyyaml>=6.0.1
Requires-Dist: rich>=13.7.0
Requires-Dist: schwifty>=2024.1.1.post0
